gclog/__init__.py
gclog/gclog.py
gclog-0.2.0.dist-info/METADATA
gclog-0.2.0.dist-info/WHEEL
gclog-0.2.0.dist-info/licenses/LICENSE
gclog-0.2.0.dist-info/RECORD
