Metadata-Version: 2.4
Name: gclog
Version: 0.2.0
Summary: Lightweight, production-ready logging package for Google Cloud Platform applications
Project-URL: Homepage, https://github.com/MarlieChiller/gcp_logger
Project-URL: Documentation, https://github.com/MarlieChiller/gcp_logger#readme
Project-URL: Repository, https://github.com/MarlieChiller/gcp_logger.git
Project-URL: Issues, https://github.com/MarlieChiller/gcp_logger/issues
Project-URL: Changelog, https://github.com/MarlieChiller/gcp_logger/releases
Author-email: marliechiller <marliechiller+pypi@proton.me>
Maintainer-email: marliechiller <marliechiller+pypi@proton.me>
License: MIT
License-File: LICENSE
Keywords: app-engine,cloud-functions,cloud-run,gcp,google-cloud,logging,loguru,structured-logging
Classifier: Development Status :: 4 - Beta
Classifier: Environment :: Web Environment
Classifier: Framework :: AsyncIO
Classifier: Intended Audience :: Developers
Classifier: License :: OSI Approved :: MIT License
Classifier: Operating System :: OS Independent
Classifier: Programming Language :: Python :: 3
Classifier: Programming Language :: Python :: 3.9
Classifier: Programming Language :: Python :: 3.10
Classifier: Programming Language :: Python :: 3.11
Classifier: Programming Language :: Python :: 3.12
Classifier: Topic :: Internet :: Log Analysis
Classifier: Topic :: Software Development :: Libraries :: Python Modules
Classifier: Topic :: System :: Logging
Requires-Python: >=3.9
Requires-Dist: loguru>=0.7.3
Requires-Dist: requests>=2.32.4
